[
    {
        "question": "Which of the following drug is preferred for skin rash in LE?",
        "exp": "Ans. c. Chloroquine. Chloroquine (Antimalarial drug) act as a systemic sunscreen by providing photoprotection. So used as prophylactic agent in LE.",
        "cop": 3,
        "opa": "Steroids",
        "opb": "Aspirin",
        "opc": "Chloroquine",
        "opd": "Azathioprine",
        "subject_name": "Skin",
        "topic_name": "Photosensitive Disorders",
        "id": "3d8e2003-7498-45e2-bdc9-b9dd5943fa6a",
        "choice_type": "single"
    },
    {
        "question": "A female presented with erythematous lesions on face with intolerance to spicy food is. Most likely diagnosis is?",
        "exp": "Ans. is 'a' i. e., Acne rosacea * Acne rosacea 8c SLE both can present with erythematous rash over face but the intolerance to spicy food indicated towards the diagnosis of acne rosacea. Acne rosacea* Acne rosacea, commonly called rosacea, is a chronic non-curable skin disease with periodic ups and down. It occurs in middle age (30-50 years). It is more common in females, but is more severe in males. Rosacea is a centrofacial disease, i. e., it involves the central face -> Cheeks, Chin, Forehead, Nose, making typical cruciate pattern of involvement. Periorbital 8c perioral areas are spared.* Clinical features are intermittant flushing followed by more permanent erythma and telangiectasia. On this back-ground, erythmatous papules, papulo pustules and rarely nodules develop.* Lesions may be exacerbated by light (photosensitive), alcohol, hot or spicy foods, emotional stress, smoking, and heat.",
        "cop": 1,
        "opa": "Acne rosacea",
        "opb": "SLE",
        "opc": "Chloasma",
        "opd": "LPP",
        "subject_name": "Skin",
        "topic_name": "Photosensitive Disorders",
        "id": "b7ccfd14-c68a-40e2-b31b-60503b70c1cd",
        "choice_type": "single"
    },
    {
        "question": "A 40 year old farmer with a history of recurrent attacks of porphyria complains of itching when exposes to the sun and maculopapular rash on sun exposed areas, his symptoms are exaggerated in the summer. The diagnosis is:",
        "exp": "Ans. is 'd' Porphyria Cutanea Tarda Sun induced maculopapular lesions, h/o recurrent attacks of porphyria are classical features of porphyria cutanea tarda. Porphyria Cutanea Tarda. Commonest* Porphyria. Sun induced subepidermal blisters on face and hands. Mostly seen in alcoholics* with liver damage. Estrogens (steroids) also aggravate itT/t - Venesection or chloroquine. Other Facts about porphyria. In acute intermittent porphyria skin lesions are absent*Other cutaneous porphyrias are: Erythropoietic porphyria. Variegate porphyria. Seborrheic Dermatitis present as greasy scales and has no relation with sunlight. Psoriasis presents as erythematous plaques topped by silvery scales*, Exposure to sunlight can aggravate psoriasis although in majority it has beneficial effect. Contact dermatitis- The lesions are usually erythematous vesicles and bullae and there will h/O exposure to allergens.",
        "cop": 4,
        "opa": "Seborrheic dermatitis",
        "opb": "Contact dermatitis",
        "opc": "Psoriasis",
        "opd": "Porphyria cutanea tarda",
        "subject_name": "Skin",
        "topic_name": "Photosensitive Disorders",
        "id": "62af374b-91cf-423d-a533-d9e56e1e039e",
        "choice_type": "single"
    },
    {
        "question": "19 year old girl presents with ligh brown pigmentation over Malar eminence, likely diagnosis is-",
        "exp": "Ans- C. The likely diagnosis could be Melasma. Following history should be noted- 1. Non pregnant female- Melasma 2. Pregnant Female- Chloasma.",
        "cop": 3,
        "opa": "Chloasma",
        "opb": "SLE",
        "opc": "Melasma",
        "opd": "Melanoma",
        "subject_name": "Skin",
        "topic_name": "Photosensitive Disorders",
        "id": "0b90104d-deb0-4830-a903-2cda8f3bdd7d",
        "choice_type": "single"
    }
]